{
 "custom_fields": [
  {
   "_assign": null, 
   "_comments": null, 
   "_liked_by": null, 
   "_user_tags": null, 
   "allow_on_submit": 0, 
   "bold": 0, 
   "collapsible": 0, 
   "collapsible_depends_on": null, 
   "columns": 0, 
   "creation": "2018-12-11 10:44:27.626528", 
   "default": null, 
   "depends_on": null, 
   "description": null, 
   "docstatus": 0, 
   "dt": "Material Request", 
   "fieldname": "material_request", 
   "fieldtype": "Read Only", 
   "hidden": 0, 
   "idx": 9, 
   "ignore_user_permissions": 0, 
   "ignore_xss_filter": 0, 
   "in_global_search": 0, 
   "in_list_view": 0, 
   "in_standard_filter": 0, 
   "insert_after": "schedule_date", 
   "label": "Material Request", 
   "modified": "2018-03-21 17:34:10.800491", 
   "modified_by": "Administrator", 
   "name": "Material Request-material_request", 
   "no_copy": 0, 
   "options": null, 
   "owner": "Administrator", 
   "parent": null, 
   "parentfield": null, 
   "parenttype": null, 
   "permlevel": 0, 
   "precision": "", 
   "print_hide": 0, 
   "print_hide_if_no_value": 0, 
   "print_width": null, 
   "read_only": 0, 
   "report_hide": 0, 
   "reqd": 0, 
   "search_index": 0, 
   "unique": 0, 
   "width": null
  }, 
  {
   "_assign": null, 
   "_comments": null, 
   "_liked_by": null, 
   "_user_tags": null, 
   "allow_on_submit": 0, 
   "bold": 0, 
   "collapsible": 0, 
   "collapsible_depends_on": null, 
   "columns": 0, 
   "creation": "2018-12-11 10:44:27.414099", 
   "default": null, 
   "depends_on": null, 
   "description": null, 
   "docstatus": 0, 
   "dt": "Material Request", 
   "fieldname": "doc_details", 
   "fieldtype": "Small Text", 
   "hidden": 0, 
   "idx": 10, 
   "ignore_user_permissions": 0, 
   "ignore_xss_filter": 0, 
   "in_global_search": 0, 
   "in_list_view": 1, 
   "in_standard_filter": 0, 
   "insert_after": "material_request", 
   "label": "Doc Details", 
   "modified": "2018-03-21 15:47:51.770649", 
   "modified_by": "Administrator", 
   "name": "Material Request-doc_details", 
   "no_copy": 0, 
   "options": null, 
   "owner": "Administrator", 
   "parent": null, 
   "parentfield": null, 
   "parenttype": null, 
   "permlevel": 0, 
   "precision": "", 
   "print_hide": 0, 
   "print_hide_if_no_value": 0, 
   "print_width": null, 
   "read_only": 1, 
   "report_hide": 0, 
   "reqd": 0, 
   "search_index": 0, 
   "unique": 0, 
   "width": null
  }, 
  {
   "_assign": null, 
   "_comments": null, 
   "_liked_by": null, 
   "_user_tags": null, 
   "allow_on_submit": 0, 
   "bold": 0, 
   "collapsible": 0, 
   "collapsible_depends_on": null, 
   "columns": 0, 
   "creation": "2018-12-11 10:44:26.440210", 
   "default": null, 
   "depends_on": null, 
   "description": null, 
   "docstatus": 0, 
   "dt": "Material Request", 
   "fieldname": "receiver", 
   "fieldtype": "Link", 
   "hidden": 0, 
   "idx": 6, 
   "ignore_user_permissions": 0, 
   "ignore_xss_filter": 0, 
   "in_global_search": 0, 
   "in_list_view": 0, 
   "in_standard_filter": 0, 
   "insert_after": "material_request_type", 
   "label": "Receiver", 
   "modified": "2018-03-21 13:11:32.070580", 
   "modified_by": "Administrator", 
   "name": "Material Request-receiver", 
   "no_copy": 0, 
   "options": "User", 
   "owner": "Administrator", 
   "parent": null, 
   "parentfield": null, 
   "parenttype": null, 
   "permlevel": 0, 
   "precision": "", 
   "print_hide": 0, 
   "print_hide_if_no_value": 0, 
   "print_width": null, 
   "read_only": 0, 
   "report_hide": 0, 
   "reqd": 0, 
   "search_index": 0, 
   "unique": 0, 
   "width": null
  }, 
  {
   "_assign": null, 
   "_comments": null, 
   "_liked_by": null, 
   "_user_tags": null, 
   "allow_on_submit": 0, 
   "bold": 0, 
   "collapsible": 0, 
   "collapsible_depends_on": null, 
   "columns": 0, 
   "creation": "2018-12-11 10:44:07.677228", 
   "default": null, 
   "depends_on": "eval:doc.material_request_type=='Purchase'", 
   "description": null, 
   "docstatus": 0, 
   "dt": "Material Request", 
   "fieldname": "section_break_0", 
   "fieldtype": "Section Break", 
   "hidden": 0, 
   "idx": 16, 
   "ignore_user_permissions": 0, 
   "ignore_xss_filter": 0, 
   "in_global_search": 0, 
   "in_list_view": 0, 
   "in_standard_filter": 0, 
   "insert_after": "supplier_details", 
   "label": "Supplier Details", 
   "modified": "2018-03-21 12:15:33.030709", 
   "modified_by": "Administrator", 
   "name": "Material Request-section_break_0", 
   "no_copy": 0, 
   "options": null, 
   "owner": "Administrator", 
   "parent": null, 
   "parentfield": null, 
   "parenttype": null, 
   "permlevel": 0, 
   "precision": null, 
   "print_hide": 0, 
   "print_hide_if_no_value": 0, 
   "print_width": null, 
   "read_only": 0, 
   "report_hide": 0, 
   "reqd": 0, 
   "search_index": 0, 
   "unique": 0, 
   "width": null
  }, 
  {
   "_assign": null, 
   "_comments": null, 
   "_liked_by": null, 
   "_user_tags": null, 
   "allow_on_submit": 0, 
   "bold": 0, 
   "collapsible": 0, 
   "collapsible_depends_on": null, 
   "columns": 0, 
   "creation": "2018-12-11 10:44:07.253565", 
   "default": null, 
   "depends_on": null, 
   "description": null, 
   "docstatus": 0, 
   "dt": "Material Request", 
   "fieldname": "column_break_0", 
   "fieldtype": "Column Break", 
   "hidden": 0, 
   "idx": 32, 
   "ignore_user_permissions": 0, 
   "ignore_xss_filter": 0, 
   "in_global_search": 0, 
   "in_list_view": 0, 
   "in_standard_filter": 0, 
   "insert_after": "cb101", 
   "label": null, 
   "modified": "2018-03-21 12:15:32.241750", 
   "modified_by": "Administrator", 
   "name": "Material Request-column_break_0", 
   "no_copy": 0, 
   "options": null, 
   "owner": "Administrator", 
   "parent": null, 
   "parentfield": null, 
   "parenttype": null, 
   "permlevel": 0, 
   "precision": null, 
   "print_hide": 0, 
   "print_hide_if_no_value": 0, 
   "print_width": null, 
   "read_only": 0, 
   "report_hide": 0, 
   "reqd": 0, 
   "search_index": 0, 
   "unique": 0, 
   "width": null
  }, 
  {
   "_assign": null, 
   "_comments": null, 
   "_liked_by": null, 
   "_user_tags": null, 
   "allow_on_submit": 0, 
   "bold": 0, 
   "collapsible": 0, 
   "collapsible_depends_on": null, 
   "columns": 0, 
   "creation": "2018-12-11 10:43:02.097395", 
   "default": null, 
   "depends_on": null, 
   "description": null, 
   "docstatus": 0, 
   "dt": "Material Request", 
   "fieldname": "cb101", 
   "fieldtype": "Column Break", 
   "hidden": 0, 
   "idx": 31, 
   "ignore_user_permissions": 0, 
   "ignore_xss_filter": 0, 
   "in_global_search": 0, 
   "in_list_view": 0, 
   "in_standard_filter": 0, 
   "insert_after": "terms", 
   "label": null, 
   "modified": "2018-03-05 16:50:46.519907", 
   "modified_by": "Administrator", 
   "name": "Material Request-cb101", 
   "no_copy": 0, 
   "options": null, 
   "owner": "Administrator", 
   "parent": null, 
   "parentfield": null, 
   "parenttype": null, 
   "permlevel": 0, 
   "precision": null, 
   "print_hide": 0, 
   "print_hide_if_no_value": 0, 
   "print_width": null, 
   "read_only": 0, 
   "report_hide": 0, 
   "reqd": 0, 
   "search_index": 0, 
   "unique": 0, 
   "width": null
  }, 
  {
   "_assign": null, 
   "_comments": null, 
   "_liked_by": null, 
   "_user_tags": null, 
   "allow_on_submit": 0, 
   "bold": 0, 
   "collapsible": 0, 
   "collapsible_depends_on": null, 
   "columns": 0, 
   "creation": "2018-12-11 10:43:01.618842", 
   "default": null, 
   "depends_on": "eval:doc.material_request_type=='Purchase'", 
   "description": null, 
   "docstatus": 0, 
   "dt": "Material Request", 
   "fieldname": "supplier_details", 
   "fieldtype": "Section Break", 
   "hidden": 0, 
   "idx": 15, 
   "ignore_user_permissions": 0, 
   "ignore_xss_filter": 0, 
   "in_global_search": 0, 
   "in_list_view": 0, 
   "in_standard_filter": 0, 
   "insert_after": "target_warehouse", 
   "label": "Supplier Details", 
   "modified": "2018-03-05 16:50:46.292216", 
   "modified_by": "Administrator", 
   "name": "Material Request-supplier_details", 
   "no_copy": 0, 
   "options": null, 
   "owner": "Administrator", 
   "parent": null, 
   "parentfield": null, 
   "parenttype": null, 
   "permlevel": 0, 
   "precision": null, 
   "print_hide": 0, 
   "print_hide_if_no_value": 0, 
   "print_width": null, 
   "read_only": 0, 
   "report_hide": 0, 
   "reqd": 0, 
   "search_index": 0, 
   "unique": 0, 
   "width": null
  }, 
  {
   "_assign": null, 
   "_comments": null, 
   "_liked_by": null, 
   "_user_tags": null, 
   "allow_on_submit": 0, 
   "bold": 0, 
   "collapsible": 0, 
   "collapsible_depends_on": null, 
   "columns": 0, 
   "creation": "2018-12-11 10:43:13.784041", 
   "default": null, 
   "depends_on": null, 
   "description": null, 
   "docstatus": 0, 
   "dt": "Material Request", 
   "fieldname": "cb123", 
   "fieldtype": "Column Break", 
   "hidden": 0, 
   "idx": 35, 
   "ignore_user_permissions": 0, 
   "ignore_xss_filter": 0, 
   "in_global_search": 0, 
   "in_list_view": 0, 
   "in_standard_filter": 0, 
   "insert_after": "method", 
   "label": null, 
   "modified": "2018-03-05 16:50:38.043547", 
   "modified_by": "Administrator", 
   "name": "Material Request-cb123", 
   "no_copy": 0, 
   "options": null, 
   "owner": "Administrator", 
   "parent": null, 
   "parentfield": null, 
   "parenttype": null, 
   "permlevel": 0, 
   "precision": null, 
   "print_hide": 0, 
   "print_hide_if_no_value": 0, 
   "print_width": null, 
   "read_only": 0, 
   "report_hide": 0, 
   "reqd": 0, 
   "search_index": 0, 
   "unique": 0, 
   "width": null
  }, 
  {
   "_assign": null, 
   "_comments": null, 
   "_liked_by": null, 
   "_user_tags": null, 
   "allow_on_submit": 0, 
   "bold": 0, 
   "collapsible": 0, 
   "collapsible_depends_on": null, 
   "columns": 0, 
   "creation": "2018-12-11 10:43:13.538049", 
   "default": null, 
   "depends_on": "eval:doc.method==\"Sea\"||doc.method==\"Air\"", 
   "description": null, 
   "docstatus": 0, 
   "dt": "Material Request", 
   "fieldname": "ship_to", 
   "fieldtype": "Select", 
   "hidden": 0, 
   "idx": 36, 
   "ignore_user_permissions": 0, 
   "ignore_xss_filter": 0, 
   "in_global_search": 0, 
   "in_list_view": 0, 
   "in_standard_filter": 0, 
   "insert_after": "cb123", 
   "label": "Ship To", 
   "modified": "2018-03-05 16:50:37.940227", 
   "modified_by": "Administrator", 
   "name": "Material Request-ship_to", 
   "no_copy": 0, 
   "options": "Jeddah Airport\nJeddah Seaport\nDammam Airpot\nDammam Seaport\nRiyadh Airpot", 
   "owner": "Administrator", 
   "parent": null, 
   "parentfield": null, 
   "parenttype": null, 
   "permlevel": 0, 
   "precision": null, 
   "print_hide": 0, 
   "print_hide_if_no_value": 0, 
   "print_width": null, 
   "read_only": 0, 
   "report_hide": 0, 
   "reqd": 0, 
   "search_index": 0, 
   "unique": 0, 
   "width": null
  }, 
  {
   "_assign": null, 
   "_comments": null, 
   "_liked_by": null, 
   "_user_tags": null, 
   "allow_on_submit": 0, 
   "bold": 0, 
   "collapsible": 0, 
   "collapsible_depends_on": null, 
   "columns": 0, 
   "creation": "2018-12-11 10:43:04.953083", 
   "default": null, 
   "depends_on": null, 
   "description": null, 
   "docstatus": 0, 
   "dt": "Material Request", 
   "fieldname": "for_warehouse", 
   "fieldtype": "Link", 
   "hidden": 0, 
   "idx": 13, 
   "ignore_user_permissions": 0, 
   "ignore_xss_filter": 0, 
   "in_global_search": 0, 
   "in_list_view": 0, 
   "in_standard_filter": 0, 
   "insert_after": "amended_from", 
   "label": "Source Warehouse", 
   "modified": "2018-03-05 16:50:33.429778", 
   "modified_by": "Administrator", 
   "name": "Material Request-for_warehouse", 
   "no_copy": 0, 
   "options": "Warehouse", 
   "owner": "Administrator", 
   "parent": null, 
   "parentfield": null, 
   "parenttype": null, 
   "permlevel": 0, 
   "precision": null, 
   "print_hide": 0, 
   "print_hide_if_no_value": 0, 
   "print_width": null, 
   "read_only": 0, 
   "report_hide": 0, 
   "reqd": 0, 
   "search_index": 0, 
   "unique": 0, 
   "width": null
  }, 
  {
   "_assign": null, 
   "_comments": null, 
   "_liked_by": null, 
   "_user_tags": null, 
   "allow_on_submit": 0, 
   "bold": 0, 
   "collapsible": 0, 
   "collapsible_depends_on": null, 
   "columns": 0, 
   "creation": "2018-12-11 10:43:04.745136", 
   "default": null, 
   "depends_on": null, 
   "description": null, 
   "docstatus": 0, 
   "dt": "Material Request", 
   "fieldname": "target_warehouse", 
   "fieldtype": "Link", 
   "hidden": 0, 
   "idx": 14, 
   "ignore_user_permissions": 0, 
   "ignore_xss_filter": 0, 
   "in_global_search": 0, 
   "in_list_view": 0, 
   "in_standard_filter": 0, 
   "insert_after": "for_warehouse", 
   "label": "Target Warehouse", 
   "modified": "2018-03-05 16:50:33.262538", 
   "modified_by": "Administrator", 
   "name": "Material Request-target_warehouse", 
   "no_copy": 0, 
   "options": "Warehouse", 
   "owner": "Administrator", 
   "parent": null, 
   "parentfield": null, 
   "parenttype": null, 
   "permlevel": 0, 
   "precision": null, 
   "print_hide": 0, 
   "print_hide_if_no_value": 0, 
   "print_width": null, 
   "read_only": 0, 
   "report_hide": 0, 
   "reqd": 0, 
   "search_index": 0, 
   "unique": 0, 
   "width": null
  }, 
  {
   "_assign": null, 
   "_comments": null, 
   "_liked_by": null, 
   "_user_tags": null, 
   "allow_on_submit": 0, 
   "bold": 0, 
   "collapsible": 0, 
   "collapsible_depends_on": null, 
   "columns": 0, 
   "creation": "2018-12-11 10:44:08.097442", 
   "default": null, 
   "depends_on": null, 
   "description": null, 
   "docstatus": 0, 
   "dt": "Material Request", 
   "fieldname": "cost_center", 
   "fieldtype": "Link", 
   "hidden": 0, 
   "idx": 2, 
   "ignore_user_permissions": 0, 
   "ignore_xss_filter": 0, 
   "in_global_search": 0, 
   "in_list_view": 0, 
   "in_standard_filter": 0, 
   "insert_after": "naming_series", 
   "label": "Cost Center", 
   "modified": "2018-02-09 16:21:24.349809", 
   "modified_by": "Administrator", 
   "name": "Material Request-cost_center", 
   "no_copy": 0, 
   "options": "Cost Center", 
   "owner": "Administrator", 
   "parent": null, 
   "parentfield": null, 
   "parenttype": null, 
   "permlevel": 0, 
   "precision": null, 
   "print_hide": 0, 
   "print_hide_if_no_value": 0, 
   "print_width": null, 
   "read_only": 0, 
   "report_hide": 0, 
   "reqd": 0, 
   "search_index": 0, 
   "unique": 0, 
   "width": null
  }, 
  {
   "_assign": null, 
   "_comments": null, 
   "_liked_by": null, 
   "_user_tags": null, 
   "allow_on_submit": 0, 
   "bold": 0, 
   "collapsible": 0, 
   "collapsible_depends_on": null, 
   "columns": 0, 
   "creation": "2018-12-11 10:44:07.889708", 
   "default": null, 
   "depends_on": null, 
   "description": null, 
   "docstatus": 0, 
   "dt": "Material Request", 
   "fieldname": "material_request_series", 
   "fieldtype": "Data", 
   "hidden": 1, 
   "idx": 3, 
   "ignore_user_permissions": 0, 
   "ignore_xss_filter": 0, 
   "in_global_search": 0, 
   "in_list_view": 0, 
   "in_standard_filter": 0, 
   "insert_after": "cost_center", 
   "label": "Material Request Series", 
   "modified": "2018-02-09 16:21:24.239518", 
   "modified_by": "Administrator", 
   "name": "Material Request-material_request_series", 
   "no_copy": 0, 
   "options": "cost_center.material_request_series", 
   "owner": "Administrator", 
   "parent": null, 
   "parentfield": null, 
   "parenttype": null, 
   "permlevel": 0, 
   "precision": null, 
   "print_hide": 0, 
   "print_hide_if_no_value": 0, 
   "print_width": null, 
   "read_only": 0, 
   "report_hide": 0, 
   "reqd": 0, 
   "search_index": 0, 
   "unique": 0, 
   "width": null
  }, 
  {
   "_assign": null, 
   "_comments": null, 
   "_liked_by": null, 
   "_user_tags": null, 
   "allow_on_submit": 0, 
   "bold": 0, 
   "collapsible": 0, 
   "collapsible_depends_on": null, 
   "columns": 0, 
   "creation": "2018-12-11 10:44:07.464354", 
   "default": null, 
   "depends_on": null, 
   "description": null, 
   "docstatus": 0, 
   "dt": "Material Request", 
   "fieldname": "supplier", 
   "fieldtype": "Link", 
   "hidden": 0, 
   "idx": 33, 
   "ignore_user_permissions": 0, 
   "ignore_xss_filter": 0, 
   "in_global_search": 0, 
   "in_list_view": 0, 
   "in_standard_filter": 0, 
   "insert_after": "column_break_0", 
   "label": "Supplier", 
   "modified": "2018-02-09 16:21:24.039218", 
   "modified_by": "Administrator", 
   "name": "Material Request-supplier", 
   "no_copy": 0, 
   "options": "Supplier", 
   "owner": "Administrator", 
   "parent": null, 
   "parentfield": null, 
   "parenttype": null, 
   "permlevel": 0, 
   "precision": null, 
   "print_hide": 0, 
   "print_hide_if_no_value": 0, 
   "print_width": null, 
   "read_only": 0, 
   "report_hide": 0, 
   "reqd": 0, 
   "search_index": 0, 
   "unique": 0, 
   "width": null
  }, 
  {
   "_assign": null, 
   "_comments": null, 
   "_liked_by": null, 
   "_user_tags": null, 
   "allow_on_submit": 0, 
   "bold": 0, 
   "collapsible": 0, 
   "collapsible_depends_on": null, 
   "columns": 0, 
   "creation": "2018-12-11 10:44:06.983314", 
   "default": null, 
   "depends_on": null, 
   "description": null, 
   "docstatus": 0, 
   "dt": "Material Request", 
   "fieldname": "location", 
   "fieldtype": "Select", 
   "hidden": 0, 
   "idx": 37, 
   "ignore_user_permissions": 0, 
   "ignore_xss_filter": 0, 
   "in_global_search": 0, 
   "in_list_view": 0, 
   "in_standard_filter": 0, 
   "insert_after": "ship_to", 
   "label": "Location", 
   "modified": "2018-02-09 16:21:23.836012", 
   "modified_by": "Administrator", 
   "name": "Material Request-location", 
   "no_copy": 0, 
   "options": "Dammam Airport\nDammam Seaport\nRiyadh Airport\nJeddah Airport\nJeddah Seaport", 
   "owner": "Administrator", 
   "parent": null, 
   "parentfield": null, 
   "parenttype": null, 
   "permlevel": 0, 
   "precision": null, 
   "print_hide": 0, 
   "print_hide_if_no_value": 0, 
   "print_width": null, 
   "read_only": 0, 
   "report_hide": 0, 
   "reqd": 0, 
   "search_index": 0, 
   "unique": 0, 
   "width": null
  }, 
  {
   "_assign": null, 
   "_comments": null, 
   "_liked_by": null, 
   "_user_tags": null, 
   "allow_on_submit": 0, 
   "bold": 0, 
   "collapsible": 0, 
   "collapsible_depends_on": null, 
   "columns": 0, 
   "creation": "2018-12-11 10:44:06.681400", 
   "default": null, 
   "depends_on": null, 
   "description": null, 
   "docstatus": 0, 
   "dt": "Material Request", 
   "fieldname": "method", 
   "fieldtype": "Select", 
   "hidden": 0, 
   "idx": 34, 
   "ignore_user_permissions": 0, 
   "ignore_xss_filter": 0, 
   "in_global_search": 0, 
   "in_list_view": 0, 
   "in_standard_filter": 0, 
   "insert_after": "supplier", 
   "label": "Method", 
   "modified": "2018-02-09 16:21:23.712578", 
   "modified_by": "Administrator", 
   "name": "Material Request-method", 
   "no_copy": 0, 
   "options": "Sea\nAir\nRoad\nCourier", 
   "owner": "Administrator", 
   "parent": null, 
   "parentfield": null, 
   "parenttype": null, 
   "permlevel": 0, 
   "precision": null, 
   "print_hide": 0, 
   "print_hide_if_no_value": 0, 
   "print_width": null, 
   "read_only": 0, 
   "report_hide": 0, 
   "reqd": 0, 
   "search_index": 0, 
   "unique": 0, 
   "width": null
  }
 ], 
 "custom_perms": [
  {
   "_assign": null, 
   "_comments": null, 
   "_liked_by": null, 
   "_user_tags": null, 
   "amend": 1, 
   "apply_user_permissions": 1, 
   "cancel": 1, 
   "create": 1, 
   "creation": "2013-03-07 14:48:38", 
   "delete": 1, 
   "docstatus": 0, 
   "email": 1, 
   "export": 0, 
   "idx": 1, 
   "if_owner": 0, 
   "import": 0, 
   "modified": "2018-03-23 16:16:53.544690", 
   "modified_by": "saleem@samltd.com", 
   "name": "12021f83ce", 
   "owner": "Administrator", 
   "parent": "Material Request", 
   "parentfield": "permissions", 
   "parenttype": "DocType", 
   "permlevel": 0, 
   "print": 1, 
   "read": 1, 
   "report": 1, 
   "role": "Purchase Manager", 
   "set_user_permissions": 0, 
   "share": 1, 
   "submit": 1, 
   "user_permission_doctypes": "[\"Company\"]", 
   "write": 1
  }, 
  {
   "_assign": null, 
   "_comments": null, 
   "_liked_by": null, 
   "_user_tags": null, 
   "amend": 1, 
   "apply_user_permissions": 1, 
   "cancel": 1, 
   "create": 1, 
   "creation": "2013-03-07 14:48:38", 
   "delete": 1, 
   "docstatus": 0, 
   "email": 1, 
   "export": 0, 
   "idx": 3, 
   "if_owner": 0, 
   "import": 0, 
   "modified": "2018-03-23 16:16:53.552462", 
   "modified_by": "saleem@samltd.com", 
   "name": "fd6bacba6e", 
   "owner": "Administrator", 
   "parent": "Material Request", 
   "parentfield": "permissions", 
   "parenttype": "DocType", 
   "permlevel": 0, 
   "print": 1, 
   "read": 1, 
   "report": 1, 
   "role": "Stock User", 
   "set_user_permissions": 0, 
   "share": 1, 
   "submit": 1, 
   "user_permission_doctypes": "[\"Company\"]", 
   "write": 1
  }, 
  {
   "_assign": null, 
   "_comments": null, 
   "_liked_by": null, 
   "_user_tags": null, 
   "amend": 1, 
   "apply_user_permissions": 1, 
   "cancel": 1, 
   "create": 1, 
   "creation": "2013-03-07 14:48:38", 
   "delete": 1, 
   "docstatus": 0, 
   "email": 1, 
   "export": 0, 
   "idx": 4, 
   "if_owner": 0, 
   "import": 0, 
   "modified": "2018-03-23 16:16:53.557554", 
   "modified_by": "saleem@samltd.com", 
   "name": "b6c569f6ff", 
   "owner": "Administrator", 
   "parent": "Material Request", 
   "parentfield": "permissions", 
   "parenttype": "DocType", 
   "permlevel": 0, 
   "print": 1, 
   "read": 1, 
   "report": 1, 
   "role": "Purchase User", 
   "set_user_permissions": 0, 
   "share": 1, 
   "submit": 1, 
   "user_permission_doctypes": "[\"Company\"]", 
   "write": 1
  }, 
  {
   "_assign": null, 
   "_comments": null, 
   "_liked_by": null, 
   "_user_tags": null, 
   "amend": 1, 
   "apply_user_permissions": 1, 
   "cancel": 1, 
   "create": 1, 
   "creation": "2013-03-07 14:48:38", 
   "delete": 1, 
   "docstatus": 0, 
   "email": 1, 
   "export": 0, 
   "idx": 2, 
   "if_owner": 0, 
   "import": 0, 
   "modified": "2018-03-23 16:16:53.562786", 
   "modified_by": "saleem@samltd.com", 
   "name": "cd4165244c", 
   "owner": "Administrator", 
   "parent": "Material Request", 
   "parentfield": "permissions", 
   "parenttype": "DocType", 
   "permlevel": 0, 
   "print": 1, 
   "read": 1, 
   "report": 1, 
   "role": "Stock Manager", 
   "set_user_permissions": 0, 
   "share": 1, 
   "submit": 1, 
   "user_permission_doctypes": "[\"Company\"]", 
   "write": 1
  }, 
  {
   "_assign": null, 
   "_comments": null, 
   "_liked_by": null, 
   "_user_tags": null, 
   "amend": 1, 
   "apply_user_permissions": 0, 
   "cancel": 1, 
   "create": 1, 
   "creation": "2018-03-24 13:40:27.621031", 
   "delete": 1, 
   "docstatus": 0, 
   "email": 1, 
   "export": 1, 
   "idx": 0, 
   "if_owner": 0, 
   "import": 1, 
   "modified": "2018-03-24 13:40:27.621031", 
   "modified_by": "Administrator", 
   "name": "3bae4df771", 
   "owner": "Administrator", 
   "parent": "Material Request", 
   "parentfield": "permissions", 
   "parenttype": "DocType", 
   "permlevel": 0, 
   "print": 1, 
   "read": 1, 
   "report": 1, 
   "role": "System Manager", 
   "set_user_permissions": 1, 
   "share": 1, 
   "submit": 1, 
   "user_permission_doctypes": null, 
   "write": 1
  }, 
  {
   "_assign": null, 
   "_comments": null, 
   "_liked_by": null, 
   "_user_tags": null, 
   "amend": 0, 
   "apply_user_permissions": 0, 
   "cancel": 0, 
   "create": 0, 
   "creation": "2018-04-12 09:44:59.492622", 
   "delete": 0, 
   "docstatus": 0, 
   "email": 0, 
   "export": 0, 
   "idx": 0, 
   "if_owner": 0, 
   "import": 0, 
   "modified": "2018-04-12 09:44:59.492622", 
   "modified_by": "Administrator", 
   "name": "1a4519f495", 
   "owner": "Administrator", 
   "parent": "Material Request", 
   "parentfield": "permissions", 
   "parenttype": "DocType", 
   "permlevel": 0, 
   "print": 1, 
   "read": 1, 
   "report": 0, 
   "role": "Print Format Manager", 
   "set_user_permissions": 0, 
   "share": 0, 
   "submit": 0, 
   "user_permission_doctypes": null, 
   "write": 0
  }, 
  {
   "_assign": null, 
   "_comments": null, 
   "_liked_by": null, 
   "_user_tags": null, 
   "amend": 0, 
   "apply_user_permissions": 0, 
   "cancel": 0, 
   "create": 1, 
   "creation": "2018-05-07 22:39:43.721637", 
   "delete": 0, 
   "docstatus": 0, 
   "email": 1, 
   "export": 1, 
   "idx": 0, 
   "if_owner": 0, 
   "import": 0, 
   "modified": "2018-05-07 22:39:43.721637", 
   "modified_by": "Administrator", 
   "name": "4245a7cfb0", 
   "owner": "Administrator", 
   "parent": "Material Request", 
   "parentfield": "permissions", 
   "parenttype": "DocType", 
   "permlevel": 0, 
   "print": 1, 
   "read": 1, 
   "report": 1, 
   "role": "Branch Accountant category 1 - JEDDAH", 
   "set_user_permissions": 0, 
   "share": 1, 
   "submit": 0, 
   "user_permission_doctypes": null, 
   "write": 1
  }, 
  {
   "_assign": null, 
   "_comments": null, 
   "_liked_by": null, 
   "_user_tags": null, 
   "amend": 0, 
   "apply_user_permissions": 0, 
   "cancel": 0, 
   "create": 1, 
   "creation": "2018-05-08 13:47:22.091349", 
   "delete": 0, 
   "docstatus": 0, 
   "email": 0, 
   "export": 0, 
   "idx": 0, 
   "if_owner": 0, 
   "import": 0, 
   "modified": "2018-05-08 13:47:22.091349", 
   "modified_by": "Administrator", 
   "name": "1445b31c07", 
   "owner": "Administrator", 
   "parent": "Material Request", 
   "parentfield": "permissions", 
   "parenttype": "DocType", 
   "permlevel": 0, 
   "print": 1, 
   "read": 1, 
   "report": 1, 
   "role": "Branch Accountant category 2 - Riyadh", 
   "set_user_permissions": 0, 
   "share": 1, 
   "submit": 1, 
   "user_permission_doctypes": "[\"Company\",\"Material Request\",\"Supplier\",\"User\"]", 
   "write": 1
  }, 
  {
   "_assign": null, 
   "_comments": null, 
   "_liked_by": null, 
   "_user_tags": null, 
   "amend": 1, 
   "apply_user_permissions": 0, 
   "cancel": 1, 
   "create": 1, 
   "creation": "2018-05-08 15:25:03.946941", 
   "delete": 0, 
   "docstatus": 0, 
   "email": 0, 
   "export": 0, 
   "idx": 0, 
   "if_owner": 0, 
   "import": 0, 
   "modified": "2018-05-08 15:25:03.946941", 
   "modified_by": "Administrator", 
   "name": "31430740ed", 
   "owner": "Administrator", 
   "parent": "Material Request", 
   "parentfield": "permissions", 
   "parenttype": "DocType", 
   "permlevel": 0, 
   "print": 1, 
   "read": 1, 
   "report": 1, 
   "role": "Branch Accountant category 3 - Alkhobar", 
   "set_user_permissions": 0, 
   "share": 1, 
   "submit": 1, 
   "user_permission_doctypes": "[\"Company\",\"Material Request\",\"User\",\"Warehouse\"]", 
   "write": 1
  }, 
  {
   "_assign": null, 
   "_comments": null, 
   "_liked_by": null, 
   "_user_tags": null, 
   "amend": 1, 
   "apply_user_permissions": 0, 
   "cancel": 1, 
   "create": 1, 
   "creation": "2018-05-09 15:04:26.612825", 
   "delete": 1, 
   "docstatus": 0, 
   "email": 0, 
   "export": 0, 
   "idx": 0, 
   "if_owner": 0, 
   "import": 0, 
   "modified": "2018-05-09 15:04:26.612825", 
   "modified_by": "Administrator", 
   "name": "3e51578511", 
   "owner": "Administrator", 
   "parent": "Material Request", 
   "parentfield": "permissions", 
   "parenttype": "DocType", 
   "permlevel": 0, 
   "print": 1, 
   "read": 1, 
   "report": 1, 
   "role": "HO accounts", 
   "set_user_permissions": 0, 
   "share": 1, 
   "submit": 1, 
   "user_permission_doctypes": null, 
   "write": 1
  }, 
  {
   "_assign": null, 
   "_comments": null, 
   "_liked_by": null, 
   "_user_tags": null, 
   "amend": 1, 
   "apply_user_permissions": 0, 
   "cancel": 1, 
   "create": 1, 
   "creation": "2018-05-09 15:14:34.848650", 
   "delete": 1, 
   "docstatus": 0, 
   "email": 0, 
   "export": 0, 
   "idx": 0, 
   "if_owner": 0, 
   "import": 0, 
   "modified": "2018-05-09 15:14:34.848650", 
   "modified_by": "Administrator", 
   "name": "e23e31f03f", 
   "owner": "Administrator", 
   "parent": "Material Request", 
   "parentfield": "permissions", 
   "parenttype": "DocType", 
   "permlevel": 0, 
   "print": 1, 
   "read": 1, 
   "report": 1, 
   "role": "Finance", 
   "set_user_permissions": 0, 
   "share": 1, 
   "submit": 1, 
   "user_permission_doctypes": null, 
   "write": 1
  }
 ], 
 "doctype": "Material Request", 
 "property_setters": [
  {
   "_assign": null, 
   "_comments": null, 
   "_liked_by": null, 
   "_user_tags": null, 
   "creation": "2018-12-11 10:44:30.558504", 
   "default_value": null, 
   "doc_type": "Material Request", 
   "docstatus": 0, 
   "doctype_or_field": "DocType", 
   "field_name": null, 
   "idx": 0, 
   "modified": "2018-03-28 10:07:41.518776", 
   "modified_by": "Administrator", 
   "name": "Material Request-read_only_onload", 
   "owner": "Administrator", 
   "parent": null, 
   "parentfield": null, 
   "parenttype": null, 
   "property": "read_only_onload", 
   "property_type": "Check", 
   "value": null
  }, 
  {
   "_assign": null, 
   "_comments": null, 
   "_liked_by": null, 
   "_user_tags": null, 
   "creation": "2018-12-11 10:44:29.197930", 
   "default_value": null, 
   "doc_type": "Material Request", 
   "docstatus": 0, 
   "doctype_or_field": "DocType", 
   "field_name": null, 
   "idx": 0, 
   "modified": "2018-03-27 14:18:07.822049", 
   "modified_by": "Administrator", 
   "name": "Material Request-title_field", 
   "owner": "Administrator", 
   "parent": null, 
   "parentfield": null, 
   "parenttype": null, 
   "property": "title_field", 
   "property_type": "Data", 
   "value": ""
  }, 
  {
   "_assign": null, 
   "_comments": null, 
   "_liked_by": null, 
   "_user_tags": null, 
   "creation": "2018-12-11 10:44:29.165879", 
   "default_value": null, 
   "doc_type": "Material Request", 
   "docstatus": 0, 
   "doctype_or_field": "DocField", 
   "field_name": "more_info", 
   "idx": 0, 
   "modified": "2018-03-27 13:34:50.242077", 
   "modified_by": "Administrator", 
   "name": "Material Request-more_info-collapsible", 
   "owner": "Administrator", 
   "parent": null, 
   "parentfield": null, 
   "parenttype": null, 
   "property": "collapsible", 
   "property_type": "Check", 
   "value": "0"
  }, 
  {
   "_assign": null, 
   "_comments": null, 
   "_liked_by": null, 
   "_user_tags": null, 
   "creation": "2018-12-11 10:44:28.977446", 
   "default_value": null, 
   "doc_type": "Material Request", 
   "docstatus": 0, 
   "doctype_or_field": "DocField", 
   "field_name": "naming_series", 
   "idx": 0, 
   "modified": "2018-03-26 15:51:56.458538", 
   "modified_by": "Administrator", 
   "name": "Material Request-naming_series-default", 
   "owner": "Administrator", 
   "parent": null, 
   "parentfield": null, 
   "parenttype": null, 
   "property": "default", 
   "property_type": "Text", 
   "value": "material_request_series."
  }, 
  {
   "_assign": null, 
   "_comments": null, 
   "_liked_by": null, 
   "_user_tags": null, 
   "creation": "2018-12-11 10:44:28.960402", 
   "default_value": null, 
   "doc_type": "Material Request", 
   "docstatus": 0, 
   "doctype_or_field": "DocField", 
   "field_name": "naming_series", 
   "idx": 0, 
   "modified": "2018-03-26 06:03:11.511205", 
   "modified_by": "Administrator", 
   "name": "Material Request-naming_series-in_list_view", 
   "owner": "Administrator", 
   "parent": null, 
   "parentfield": null, 
   "parenttype": null, 
   "property": "in_list_view", 
   "property_type": "Check", 
   "value": "0"
  }, 
  {
   "_assign": null, 
   "_comments": null, 
   "_liked_by": null, 
   "_user_tags": null, 
   "creation": "2018-12-11 10:44:29.370055", 
   "default_value": null, 
   "doc_type": "Material Request", 
   "docstatus": 0, 
   "doctype_or_field": "DocField", 
   "field_name": "naming_series", 
   "idx": 0, 
   "modified": "2018-03-07 10:09:34.688456", 
   "modified_by": "Administrator", 
   "name": "Material Request-naming_series-options", 
   "owner": "Administrator", 
   "parent": null, 
   "parentfield": null, 
   "parenttype": null, 
   "property": "options", 
   "property_type": "Text", 
   "value": "material_request_series."
  }
 ], 
 "sync_on_migrate": 1
}